RedisServer_Queue/RedisServer.py
RedisServer_Queue-0.0.4.dist-info/LICENSE
RedisServer_Queue-0.0.4.dist-info/METADATA
RedisServer_Queue-0.0.4.dist-info/WHEEL
RedisServer_Queue-0.0.4.dist-info/top_level.txt
RedisServer_Queue-0.0.4.dist-info/RECORD
