Metadata-Version: 2.1
Name: RedisServer-Queue
Version: 0.0.4
Summary: RedisServer-Queue is a simple redis server
Author-email: NelsonLongXiang <1169207670@qq.com>
Project-URL: Homepage, https://github.com/NelsonLongxiang/RedisServer
Project-URL: Issues, https://github.com/NelsonLongxiang/RedisServer/issues
Classifier: Programming Language :: Python :: 3
Classifier: License :: OSI Approved :: MIT License
Classifier: Operating System :: OS Independent
Requires-Python: >=3.9
License-File: LICENSE
